[
    {
        "firstName": "ROBERT",
        "lastName": "SCRANTOM",
        "phone": "9726390588",
        "address": "755 YELLOWSTONE DR",
        "city": "ALLEN",
        "state": "TX",
        "zip": "75002",
        "email": "ROBERTSCRANTOM@YAHOO.COM",
        "dateOfBirth": "1970-03-15T12:00:00",
        "ssn": "458512655",
        "userOrders": null,
        "isSold": false,
        "id": 48545
    },
    {
        "firstName": "DEVIN",
        "lastName": "WHITE",
        "phone": "7577774543",
        "address": "15012 FERNHILL DR",
        "city": "AUSTIN",
        "state": "TX",
        "zip": "78717",
        "email": "DNRWHITE01@GMAIL.COM",
        "dateOfBirth": "1970-01-29T12:00:00",
        "ssn": "592051668",
        "userOrders": null,
        "isSold": false,
        "id": 48553
    },
    {
        "firstName": "GRAZIANA",
        "lastName": "PALAZZO",
        "phone": "3055054515",
        "address": "4141 NAUTILUS DR APT 5C",
        "city": "M*B",
        "state": "BEACH",
        "zip": "33140",
        "email": "GRAZIANACONZ@YAHOO.COM",
        "dateOfBirth": "1970-12-07T12:00:00",
        "ssn": "593776853",
        "userOrders": null,
        "isSold": false,
        "id": 48586
    },
    {
        "firstName": "BRANDI",
        "lastName": "HOMOYA",
        "phone": "6189422872",
        "address": "PO BOX 136",
        "city": "MARINA",
        "state": "IL",
        "zip": "93933",
        "email": "BRANDIMCGEE70@GMAIL.COM",
        "dateOfBirth": "1970-07-30T12:00:00",
        "ssn": "320646706",
        "userOrders": null,
        "isSold": false,
        "id": 48634
    },
    {
        "firstName": "TONJE",
        "lastName": "SNOW",
        "phone": "8474310505",
        "address": "241 CUMBERLAND AVE",
        "city": "KENLWRTH",
        "state": "IL",
        "zip": "60043",
        "email": "T.KILEN@YAHOO.COM",
        "dateOfBirth": "1970-06-24T12:00:00",
        "ssn": "360749708",
        "userOrders": null,
        "isSold": false,
        "id": 48673
    },
    {
        "firstName": "MARK",
        "lastName": "JOHNSON",
        "phone": "9132404041",
        "address": "4413 N 142ND ST",
        "city": "BASEHOR",
        "state": "KS",
        "zip": "66007",
        "email": "MOJO197009@YAHOO.COM",
        "dateOfBirth": "1970-09-15T12:00:00",
        "ssn": "421988574",
        "userOrders": null,
        "isSold": true,
        "id": 48785
    },
    {
        "firstName": "AUDERIA",
        "lastName": "IBARRA",
        "phone": "8179752164",
        "address": "1660 FAGAN DR",
        "city": "BLUE MOUND",
        "state": "MOUND",
        "zip": "76131",
        "email": "AUDELIA11570@GMAIL.COM",
        "dateOfBirth": "1970-01-14T12:00:00",
        "ssn": "572834472",
        "userOrders": null,
        "isSold": false,
        "id": 48789
    },
    {
        "firstName": "SANDRA",
        "lastName": "KISCHUK",
        "phone": "2482300678",
        "address": "102 N MAIN ST",
        "city": "MARINE CITY",
        "state": "CITY",
        "zip": "48039",
        "email": "RANTIQUESLLC@GMAIL.COM",
        "dateOfBirth": "1970-06-30T12:00:00",
        "ssn": "363988296",
        "userOrders": null,
        "isSold": false,
        "id": 48994
    },
    {
        "firstName": "AMY",
        "lastName": "K",
        "phone": "8622661097",
        "address": "352 MILES BRANCH RD",
        "city": "CHPL HL",
        "state": "NC",
        "zip": "27516",
        "email": "AMYVDP@HOTMAIL.COM",
        "dateOfBirth": "1970-03-28T12:00:00",
        "ssn": "153608927",
        "userOrders": null,
        "isSold": false,
        "id": 48997
    },
    {
        "firstName": "JUANA",
        "lastName": "PENA",
        "phone": "1111110001",
        "address": "3632 2ND AVE",
        "city": "LA",
        "state": "ANGELES",
        "zip": "90018",
        "email": "JUANA.PENA@ATT.NET",
        "dateOfBirth": "1970-08-21T12:00:00",
        "ssn": "616363793",
        "userOrders": null,
        "isSold": false,
        "id": 49012
    },
    {
        "firstName": "RANA",
        "lastName": "JENNINGS",
        "phone": "9165493684",
        "address": "1115 DAYTON ST",
        "city": "SAC",
        "state": "CO",
        "zip": "95820",
        "email": "RLJENNINGS70@YAHOO.COM",
        "dateOfBirth": "1970-09-07T12:00:00",
        "ssn": "569233726",
        "userOrders": null,
        "isSold": true,
        "id": 49098
    },
    {
        "firstName": "DORTE",
        "lastName": "VIND",
        "phone": "5103252697",
        "address": "1118 EUREKA LN APT 1",
        "city": "CNCD",
        "state": "CA",
        "zip": "94520",
        "email": "DORTEVTHOMAS@EARTHLINK.NET",
        "dateOfBirth": "1970-09-02T12:00:00",
        "ssn": "625903316",
        "userOrders": null,
        "isSold": false,
        "id": 49126
    },
    {
        "firstName": "PAULA",
        "lastName": "RENFRO",
        "phone": "3176258489",
        "address": "1031 NEW AMSTERDAM DR",
        "city": "GREENWOOD",
        "state": "IN",
        "zip": "46142",
        "email": "PAULA_RENFRO@YAHOO.COM",
        "dateOfBirth": "1970-02-14T12:00:00",
        "ssn": "306947293",
        "userOrders": null,
        "isSold": false,
        "id": 49166
    },
    {
        "firstName": "COREY",
        "lastName": "NEAL",
        "phone": "1111110003",
        "address": "7253 WESTPORT LOOP",
        "city": "COLS",
        "state": "GA",
        "zip": "31820",
        "email": "COREYNEAL717@GMAIL.COM",
        "dateOfBirth": "1970-08-16T12:00:00",
        "ssn": "451453198",
        "userOrders": null,
        "isSold": false,
        "id": 49179
    },
    {
        "firstName": "MARNA",
        "lastName": "EISSA",
        "phone": "5047820332",
        "address": "119 E OAKRIDGE PARK",
        "city": "METAIRIE",
        "state": "LA",
        "zip": "70005",
        "email": "MJEISSA@COX.NET",
        "dateOfBirth": "1970-02-08T12:00:00",
        "ssn": "190663080",
        "userOrders": null,
        "isSold": false,
        "id": 49196
    }
]