[
    {
        "firstName": "KATHY",
        "lastName": "PARKER",
        "phone": "8702176890",
        "address": "602 MCLAIN ST",
        "city": "NEWPORT",
        "state": "AR",
        "zip": "72112",
        "email": "JOLEFTY37@YAHOO.COM",
        "dateOfBirth": "1972-01-28T12:00:00",
        "ssn": "431437639",
        "userOrders": null,
        "isSold": true,
        "id": 62634
    },
    {
        "firstName": "CHRISTOPHER",
        "lastName": "WINDISCH",
        "phone": "8183120117",
        "address": "5836 STONECREST DR",
        "city": "AGRA HLS",
        "state": "HILLS",
        "zip": "91301",
        "email": "WINDISCHKRISTA@HOTMAIL.COM",
        "dateOfBirth": "1972-09-28T12:00:00",
        "ssn": "548574982",
        "userOrders": null,
        "isSold": false,
        "id": 62640
    },
    {
        "firstName": "CRAIG",
        "lastName": "EGGERT",
        "phone": "6304059244",
        "address": "23747 SPRINGS CT UNIT 117",
        "city": "PLAINFLD",
        "state": "IL",
        "zip": "60585",
        "email": "CEGGERT429@GMAIL.COM",
        "dateOfBirth": "1972-12-19T12:00:00",
        "ssn": "328802536",
        "userOrders": null,
        "isSold": false,
        "id": 62678
    },
    {
        "firstName": "DELMI",
        "lastName": "TURCIOS",
        "phone": "3172581506",
        "address": "1110 SHADOWVIEW WAY",
        "city": "INDIANAPOLIS",
        "state": "IN",
        "zip": "46241",
        "email": "DELMIELVIR317@GMAIL.COM",
        "dateOfBirth": "1972-08-05T12:00:00",
        "ssn": "925924510",
        "userOrders": null,
        "isSold": false,
        "id": 62703
    },
    {
        "firstName": "SCOTT",
        "lastName": "PODOLAN",
        "phone": "6142142577",
        "address": "2117 SCOTTINGHAM DR",
        "city": "COLUMBUS",
        "state": "OH",
        "zip": "43016",
        "email": "SPODOLAN@SBCGLOBAL.NET",
        "dateOfBirth": "1972-06-27T12:00:00",
        "ssn": "285646336",
        "userOrders": null,
        "isSold": false,
        "id": 62775
    },
    {
        "firstName": "KENNETH",
        "lastName": "LYNCH",
        "phone": "4042429390",
        "address": "8791 FREEDOM WAY",
        "city": "JNSBRO",
        "state": "GA",
        "zip": "30238",
        "email": "NORCROSSSONY@YAHOO.COM",
        "dateOfBirth": "1972-07-20T12:00:00",
        "ssn": "365797765",
        "userOrders": null,
        "isSold": false,
        "id": 62862
    },
    {
        "firstName": "DANA",
        "lastName": "RAMSEY",
        "phone": "5012091992",
        "address": "ETNA INSURANCE",
        "city": "GARLAND COUNTY",
        "state": "CORDOBA",
        "zip": "71949",
        "email": "DANARAM@ATT.NET",
        "dateOfBirth": "1972-04-27T12:00:00",
        "ssn": "431654145",
        "userOrders": null,
        "isSold": false,
        "id": 63020
    },
    {
        "firstName": "CORY",
        "lastName": "AYERS",
        "phone": "9316452358",
        "address": "510 E CHRISTY ST",
        "city": "CLARKSVILLE",
        "state": "IN",
        "zip": "37040",
        "email": "MYSHYAYERS@YAHOO.COM",
        "dateOfBirth": "1972-02-08T12:00:00",
        "ssn": "171580965",
        "userOrders": null,
        "isSold": false,
        "id": 63078
    },
    {
        "firstName": "ERNEST",
        "lastName": "MCCULLEN",
        "phone": "1111110001",
        "address": "616 S MADISON AVE",
        "city": "GLDSBRO",
        "state": "NC",
        "zip": "27530",
        "email": "CARRIERICHARDSON316@LIVE.COM",
        "dateOfBirth": "1972-12-10T12:00:00",
        "ssn": "102563952",
        "userOrders": null,
        "isSold": false,
        "id": 63086
    },
    {
        "firstName": "TAMMARA",
        "lastName": "KNIGHT",
        "phone": "7854070432",
        "address": "132 S ROCK ST",
        "city": "MINNEAPOLIS",
        "state": "KS",
        "zip": "67467",
        "email": "TLKNIGHT2006@GMAIL.COM",
        "dateOfBirth": "1972-10-10T12:00:00",
        "ssn": "509942015",
        "userOrders": null,
        "isSold": true,
        "id": 63124
    },
    {
        "firstName": "JAMES",
        "lastName": "BROWN",
        "phone": "4057931338",
        "address": "211 BELLAIRE DR",
        "city": "MOORE",
        "state": "OK",
        "zip": "73160",
        "email": "JANACBANANA@HOTMAIL.COM",
        "dateOfBirth": "1972-12-15T12:00:00",
        "ssn": "525436929",
        "userOrders": null,
        "isSold": false,
        "id": 63199
    },
    {
        "firstName": "SHAWN",
        "lastName": "JOSEPH",
        "phone": "6623463831",
        "address": "414 N GREEN ST",
        "city": "TUPELO",
        "state": "MS",
        "zip": "38804",
        "email": "JOSEPH9012@ATT.NET",
        "dateOfBirth": "1972-07-06T12:00:00",
        "ssn": "318692189",
        "userOrders": null,
        "isSold": false,
        "id": 63243
    },
    {
        "firstName": "MARK",
        "lastName": "PORTER",
        "phone": "8322501828",
        "address": "16102 BURBERRY CIR",
        "city": "HOUSTON",
        "state": "TX",
        "zip": "77044",
        "email": "MJPORTER817@HOTMAIL.COM",
        "dateOfBirth": "1972-08-17T12:00:00",
        "ssn": "465539378",
        "userOrders": null,
        "isSold": false,
        "id": 63338
    },
    {
        "firstName": "EMILY",
        "lastName": "DURON",
        "phone": "2106690395",
        "address": "2601 AVENUE K",
        "city": "HONDO",
        "state": "TX",
        "zip": "78861",
        "email": "MEDURON@SBCGLOBAL.NET",
        "dateOfBirth": "1972-06-27T12:00:00",
        "ssn": "463575468",
        "userOrders": null,
        "isSold": false,
        "id": 63349
    },
    {
        "firstName": "HECTOR",
        "lastName": "MERCADO",
        "phone": "5595174879",
        "address": "1407 LINDA MESA DR",
        "city": "MDRA",
        "state": "CA",
        "zip": "93638",
        "email": "HECMERC72@YAHOO.COM",
        "dateOfBirth": "1972-07-13T12:00:00",
        "ssn": "609988708",
        "userOrders": null,
        "isSold": false,
        "id": 63488
    }
]