[
    {
        "firstName": "ROBERT",
        "lastName": "VRASTIL",
        "phone": "7084294322",
        "address": "8127 MEADOW LN",
        "city": "TINLY PK",
        "state": "PARK",
        "zip": "60477",
        "email": "JARLIN43@BELLSOUTH.NET",
        "dateOfBirth": "1972-11-07T12:00:00",
        "ssn": "351788417",
        "userOrders": null,
        "isSold": false,
        "id": 25589
    },
    {
        "firstName": "KELLY",
        "lastName": "HAGERMAN",
        "phone": "2623448892",
        "address": "1116 61ST ST",
        "city": "KENOSHA",
        "state": "WI",
        "zip": "53143",
        "email": "DOMINIQUE7189@ATT.NET",
        "dateOfBirth": "1972-01-07T12:00:00",
        "ssn": "472868883",
        "userOrders": null,
        "isSold": false,
        "id": 25640
    },
    {
        "firstName": "MARIS",
        "lastName": "DUNN",
        "phone": "6783828829",
        "address": "208 WESTWOOD TRL",
        "city": "DLS",
        "state": "GA",
        "zip": "30132",
        "email": "MARIS.DUNN@FIRSTDATA.COM",
        "dateOfBirth": "1972-02-13T12:00:00",
        "ssn": "516800665",
        "userOrders": null,
        "isSold": false,
        "id": 25641
    },
    {
        "firstName": "ERNESTINE",
        "lastName": "MORGAN",
        "phone": "5177061213",
        "address": "7113 E M 78 APT A9",
        "city": "BATH TWP",
        "state": "LANSING",
        "zip": "48823",
        "email": "TINA.MORGAN63123@GMAIL.COM",
        "dateOfBirth": "1972-07-22T12:00:00",
        "ssn": "382883093",
        "userOrders": null,
        "isSold": false,
        "id": 25652
    },
    {
        "firstName": "JAVIER",
        "lastName": "GUAJARDO",
        "phone": "9726392308",
        "address": "1414 HICKORY ST",
        "city": "GRAND PRAIRIE",
        "state": "PRAIRIE",
        "zip": "75050",
        "email": "GUAJARDO.PATRICIA@ATT.NET",
        "dateOfBirth": "1972-12-11T12:00:00",
        "ssn": "515787445",
        "userOrders": null,
        "isSold": false,
        "id": 25665
    },
    {
        "firstName": "SPENCER",
        "lastName": "MCKEIVER",
        "phone": "9044221121",
        "address": "2577 BARRY DR S",
        "city": "JKVL",
        "state": "FL",
        "zip": "32208",
        "email": "SDMCKELVER@GMAIL.COM",
        "dateOfBirth": "1972-09-01T12:00:00",
        "ssn": "264814238",
        "userOrders": null,
        "isSold": false,
        "id": 25684
    },
    {
        "firstName": "JENISE",
        "lastName": "REYNOLDS",
        "phone": "9253624400",
        "address": "2571 SHADOW MOUNTAIN DR",
        "city": "SN RMN",
        "state": "RAMON",
        "zip": "94583",
        "email": "LAKERS8@SBCGLOBAL.NET",
        "dateOfBirth": "1972-12-13T12:00:00",
        "ssn": "605074153",
        "userOrders": null,
        "isSold": true,
        "id": 25769
    },
    {
        "firstName": "JACK",
        "lastName": "HITSMAN",
        "phone": "6169352911",
        "address": "15891 GROESBECK ST",
        "city": "GRAND HAVEN TWP",
        "state": "HAVEN",
        "zip": "49417",
        "email": "JACK@SPRINT.BLACKBERRY.NET",
        "dateOfBirth": "1972-11-14T12:00:00",
        "ssn": "372883101",
        "userOrders": null,
        "isSold": false,
        "id": 25781
    },
    {
        "firstName": "ANA",
        "lastName": "ZARAGOZA",
        "phone": "6612086197",
        "address": "5250 KNUDSEN DR UNIT B",
        "city": "BKFD",
        "state": "CA",
        "zip": "93308",
        "email": "ANAYARECHCEJA@YAHOO.COM",
        "dateOfBirth": "1972-03-29T12:00:00",
        "ssn": "311194817",
        "userOrders": null,
        "isSold": false,
        "id": 25849
    },
    {
        "firstName": "MALGORTZATA",
        "lastName": "LISIECKI",
        "phone": "6302202980",
        "address": "790 CASE DR",
        "city": "ROSEL",
        "state": "IL",
        "zip": "60172",
        "email": "GOSIA_LISEK@SBCGLOBAL.NET",
        "dateOfBirth": "1972-11-16T12:00:00",
        "ssn": "355827316",
        "userOrders": null,
        "isSold": false,
        "id": 25935
    },
    {
        "firstName": "MELISSA",
        "lastName": "FREDERIKSEN",
        "phone": "6155222988",
        "address": "1000 BATTLEFIELD DR",
        "city": "NASHVILLE",
        "state": "TN",
        "zip": "37204",
        "email": "MDF13672@GMAIL.COM",
        "dateOfBirth": "1972-06-13T12:00:00",
        "ssn": "386745596",
        "userOrders": null,
        "isSold": false,
        "id": 26012
    },
    {
        "firstName": "SHONIQUE",
        "lastName": "S",
        "phone": "2102740375",
        "address": "14336 ISLAND POINT DR",
        "city": "EL PASO",
        "state": "PASO",
        "zip": "79938",
        "email": "CHOCODRP@GMAIL.COM",
        "dateOfBirth": "1972-09-22T12:00:00",
        "ssn": "454311381",
        "userOrders": null,
        "isSold": false,
        "id": 26016
    },
    {
        "firstName": "SRIDHAR",
        "lastName": "VALLURU",
        "phone": "1111110001",
        "address": "5300 ANACONDA LN",
        "city": "AUSTIN",
        "state": "TX",
        "zip": "78730",
        "email": "VALLURU@YAHOO.COM",
        "dateOfBirth": "1972-06-22T12:00:00",
        "ssn": "642365092",
        "userOrders": null,
        "isSold": false,
        "id": 26018
    },
    {
        "firstName": "SANDY",
        "lastName": "ALEXANDER",
        "phone": "9064401618",
        "address": "1711 RYAN AVE",
        "city": "SAULT STE MARIE",
        "state": "S",
        "zip": "49783",
        "email": "AGENT99@LIGHTHOUSE.NET",
        "dateOfBirth": "1972-03-29T12:00:00",
        "ssn": "380663699",
        "userOrders": null,
        "isSold": false,
        "id": 26061
    },
    {
        "firstName": "MICHELLE",
        "lastName": "THOMAS",
        "phone": "4697357203",
        "address": "PO BOX 850038",
        "city": "MESQUITE",
        "state": "TX",
        "zip": "75149",
        "email": "MFTHOMAS72@YAHOO.COM",
        "dateOfBirth": "1972-01-20T12:00:00",
        "ssn": "446746539",
        "userOrders": null,
        "isSold": false,
        "id": 26147
    }
]