[
    {
        "firstName": "JOHN",
        "lastName": "LAMBERT",
        "phone": "4049854224",
        "address": "3335 RIVER HEIGHTS XING SE",
        "city": "MRETA",
        "state": "GA",
        "zip": "30067",
        "email": "JLAMBERT874@YAHOO.COM.COM",
        "dateOfBirth": "1974-08-02T12:00:00",
        "ssn": "182646256",
        "userOrders": null,
        "isSold": false,
        "id": 99191
    },
    {
        "firstName": "CHARLES",
        "lastName": "KING",
        "phone": "3134129784",
        "address": "1412 HELEN ST",
        "city": "DETROIT",
        "state": "MI",
        "zip": "48207",
        "email": "SEXYEJONES@GMAIL.COM",
        "dateOfBirth": "1974-09-25T12:00:00",
        "ssn": "376782898",
        "userOrders": null,
        "isSold": false,
        "id": 99222
    },
    {
        "firstName": "IMTIAZ",
        "lastName": "RASUL",
        "phone": "9042956346",
        "address": "132 PETER ISLAND DR",
        "city": "ST AUG",
        "state": "AUGUSTINE",
        "zip": "32092",
        "email": "IRASULPK@GMAIL.COM",
        "dateOfBirth": "1974-03-03T12:00:00",
        "ssn": "511230009",
        "userOrders": null,
        "isSold": false,
        "id": 99225
    },
    {
        "firstName": "JAMES",
        "lastName": "OHLEN",
        "phone": "5126803113",
        "address": "801 W 5TH ST APT 2608",
        "city": "AUSTIN",
        "state": "TX",
        "zip": "78701",
        "email": "TTTX33@GMAIL.COM",
        "dateOfBirth": "1974-03-16T12:00:00",
        "ssn": "633024956",
        "userOrders": null,
        "isSold": false,
        "id": 99238
    },
    {
        "firstName": "SHAYNE",
        "lastName": "THOMAS",
        "phone": "8178548521",
        "address": "9964 LONE EAGLE DR",
        "city": "FORT WORTH",
        "state": "WORTH",
        "zip": "76108",
        "email": "THOM9964@SBCGLOBAL.NET",
        "dateOfBirth": "1974-01-21T12:00:00",
        "ssn": "437577166",
        "userOrders": null,
        "isSold": false,
        "id": 99253
    },
    {
        "firstName": "DAWN",
        "lastName": "SCHREINER",
        "phone": "8596091188",
        "address": "11990 BEACH BLVD APT 178",
        "city": "JKVL",
        "state": "FL",
        "zip": "32246",
        "email": "TCHRDAWN@HOTMAIL.COM",
        "dateOfBirth": "1974-12-09T12:00:00",
        "ssn": "400312499",
        "userOrders": null,
        "isSold": false,
        "id": 99477
    },
    {
        "firstName": "NINA",
        "lastName": "MILES",
        "phone": "2562639921",
        "address": "4908 COUNTY ROAD 31",
        "city": "KILLEN",
        "state": "AL",
        "zip": "35645",
        "email": "NINAVMILES@GMAIL.COM",
        "dateOfBirth": "1974-05-23T12:00:00",
        "ssn": "420475423",
        "userOrders": null,
        "isSold": false,
        "id": 99486
    },
    {
        "firstName": "MICHAEL",
        "lastName": "BISHOP",
        "phone": "7735029614",
        "address": "1545 N LAUREL AVE APT 102",
        "city": "LA",
        "state": "ANGELES",
        "zip": "90046",
        "email": "MBISHOP2112@GMAIL.COM",
        "dateOfBirth": "1974-01-23T12:00:00",
        "ssn": "365967167",
        "userOrders": null,
        "isSold": false,
        "id": 99519
    },
    {
        "firstName": "ALISA",
        "lastName": "KELSEY",
        "phone": "3134103030",
        "address": "8342 ROSELAWN ST",
        "city": "DETROIT",
        "state": "MI",
        "zip": "48238",
        "email": "ALKELSEY@ATT.NET",
        "dateOfBirth": "1974-09-24T12:00:00",
        "ssn": "377808290",
        "userOrders": null,
        "isSold": false,
        "id": 99649
    },
    {
        "firstName": "BEATRIZ",
        "lastName": "LIZAMA",
        "phone": "5597506122",
        "address": "3844 S SHADY ST",
        "city": "VIS",
        "state": "CA",
        "zip": "93277",
        "email": "BEATRIZLIZAMA831@GMAIL.COM",
        "dateOfBirth": "1974-10-15T12:00:00",
        "ssn": "568335846",
        "userOrders": null,
        "isSold": false,
        "id": 99673
    },
    {
        "firstName": "NATALEE",
        "lastName": "ROWLAND",
        "phone": "7656439596",
        "address": "9189 BRIAR DR",
        "city": "ANDERSON",
        "state": "IN",
        "zip": "46013",
        "email": "NATALEE.ROWLAND@ATT.NET",
        "dateOfBirth": "1974-07-15T12:00:00",
        "ssn": "305048074",
        "userOrders": null,
        "isSold": false,
        "id": 99732
    },
    {
        "firstName": "HOLLY",
        "lastName": "SCHMIDT",
        "phone": "2144489232",
        "address": "3616 BLUE CLOUD DR",
        "city": "NEW BRAUNFELS",
        "state": "BRAUNFELS",
        "zip": "78130",
        "email": "HOLLYMTX@GMAIL.COM",
        "dateOfBirth": "1974-12-18T12:00:00",
        "ssn": "451975235",
        "userOrders": null,
        "isSold": true,
        "id": 99761
    },
    {
        "firstName": "KELLY",
        "lastName": "WOOLVERTON",
        "phone": "4174662979",
        "address": "492 GALLOWAY DR",
        "city": "GREENE COUNTY",
        "state": "MO",
        "zip": "65742",
        "email": "KLLYWLVRTN@YAHOO.COM",
        "dateOfBirth": "1974-04-17T12:00:00",
        "ssn": "511821553",
        "userOrders": null,
        "isSold": false,
        "id": 99808
    },
    {
        "firstName": "JANNA",
        "lastName": "BENNETT",
        "phone": "3177801909",
        "address": "1609 TULIP DR",
        "city": "INDIANAPOLIS",
        "state": "IN",
        "zip": "46220",
        "email": "JANNA.M.BENNETT@GMAIL.COM",
        "dateOfBirth": "1974-04-21T12:00:00",
        "ssn": "305740066",
        "userOrders": null,
        "isSold": false,
        "id": 99855
    },
    {
        "firstName": "CHARITY",
        "lastName": "MACKENZIE",
        "phone": "1111110001",
        "address": "1822 AMERICAN ELM CT",
        "city": "STERRETT",
        "state": "LAND",
        "zip": "35147",
        "email": "CHARITYANDJAE@BELLSOUTH.NET",
        "dateOfBirth": "1974-01-19T12:00:00",
        "ssn": "438575008",
        "userOrders": null,
        "isSold": true,
        "id": 99884
    }
]