[
    {
        "firstName": "PATRICIA",
        "lastName": "ALCALA",
        "phone": "5596260568",
        "address": "1031 E EARLY AVE",
        "city": "ORG CV",
        "state": "CA",
        "zip": "93646",
        "email": "PATTYALCALA8040@YAHOO.COM",
        "dateOfBirth": "1979-05-25T12:00:00",
        "ssn": "549654172",
        "userOrders": null,
        "isSold": false,
        "id": 47094
    },
    {
        "firstName": "JEFFREY",
        "lastName": "WEAVER",
        "phone": "2819221178",
        "address": "11535 HIGHLAND MEADOW DR",
        "city": "HOUSTON",
        "state": "TX",
        "zip": "77089",
        "email": "QUEEN_WEAVER@YAHOO.COM",
        "dateOfBirth": "1979-03-19T12:00:00",
        "ssn": "460854096",
        "userOrders": null,
        "isSold": false,
        "id": 47135
    },
    {
        "firstName": "CHRISTINA",
        "lastName": "DUNCAN",
        "phone": "7049052431",
        "address": "14 E CAVEN ST",
        "city": "INDIANAPOLIS",
        "state": "IN",
        "zip": "46225",
        "email": "GRNIDHOTEE@YAHOO.COM",
        "dateOfBirth": "1979-04-14T12:00:00",
        "ssn": "314904273",
        "userOrders": null,
        "isSold": false,
        "id": 47171
    },
    {
        "firstName": "FRANK",
        "lastName": "MILES",
        "phone": "8035562117",
        "address": "1301 JAYNE LN",
        "city": "LEXTN",
        "state": "COLUMBIA",
        "zip": "29073",
        "email": "SKYMAN1979@ATT.COM",
        "dateOfBirth": "1979-03-28T12:00:00",
        "ssn": "248413527",
        "userOrders": null,
        "isSold": false,
        "id": 47336
    },
    {
        "firstName": "SREECHANDRA",
        "lastName": "DONEPUDI",
        "phone": "5018311635",
        "address": "505 EDGEMORE AVE",
        "city": "CARY",
        "state": "NC",
        "zip": "27519",
        "email": "SREECHANDRADONEPUDI-ACCOUNTS@YAHOO.COM",
        "dateOfBirth": "1979-05-10T12:00:00",
        "ssn": "439633216",
        "userOrders": null,
        "isSold": false,
        "id": 47356
    },
    {
        "firstName": "HANY",
        "lastName": "TAWFIK",
        "phone": "7088339974",
        "address": "7531 175TH ST APT 424",
        "city": "TINLY PK",
        "state": "PARK",
        "zip": "60477",
        "email": "HANYTAWFIK90@YAHOO.COM",
        "dateOfBirth": "1979-06-25T12:00:00",
        "ssn": "356048825",
        "userOrders": null,
        "isSold": false,
        "id": 47372
    },
    {
        "firstName": "JOSIE",
        "lastName": "GARCIA",
        "phone": "9512058007",
        "address": "718 JUNE DR",
        "city": "COR",
        "state": "CA",
        "zip": "92879",
        "email": "JOSIEGARCIA138@HOTMAIL.COM",
        "dateOfBirth": "1979-01-04T12:00:00",
        "ssn": "623017035",
        "userOrders": null,
        "isSold": false,
        "id": 47552
    },
    {
        "firstName": "MARIA",
        "lastName": "OLALDE",
        "phone": "6788591049",
        "address": "1707 LAKEVIEW CIR",
        "city": "GANV",
        "state": "GA",
        "zip": "30501",
        "email": "MARIA.OLALDE@GCSSK12.NET",
        "dateOfBirth": "1979-01-18T12:00:00",
        "ssn": "644186840",
        "userOrders": null,
        "isSold": false,
        "id": 47727
    },
    {
        "firstName": "KEVIN",
        "lastName": "RUDROFF",
        "phone": "3146869362",
        "address": "44 OAKWOOD LN",
        "city": "ST LOUIS",
        "state": "LOUIS",
        "zip": "63104",
        "email": "KEV91579@ME.COM",
        "dateOfBirth": "1979-09-15T12:00:00",
        "ssn": "489980448",
        "userOrders": null,
        "isSold": false,
        "id": 47732
    },
    {
        "firstName": "EDWIN",
        "lastName": "CORNEJO",
        "phone": "7032165487",
        "address": "43185 KATAMA SQ",
        "city": "CHANTILLY",
        "state": "VA",
        "zip": "20152",
        "email": "PROGRESSIVE.DJ27@GMAIL.COM",
        "dateOfBirth": "1979-08-26T12:00:00",
        "ssn": "231194231",
        "userOrders": null,
        "isSold": false,
        "id": 47769
    },
    {
        "firstName": "JEFF",
        "lastName": "JACOBS",
        "phone": "9134841038",
        "address": "13005 W 138TH ST",
        "city": "OVERLAND PARK",
        "state": "PARK",
        "zip": "66221",
        "email": "TRICIAZERGER@GMAIL.COM",
        "dateOfBirth": "1979-01-11T12:00:00",
        "ssn": "498966244",
        "userOrders": null,
        "isSold": false,
        "id": 47829
    },
    {
        "firstName": "GHANDI",
        "lastName": "TOUMA",
        "phone": "6192191635",
        "address": "166 N 1ST ST UNIT 8",
        "city": "EL CAJ",
        "state": "CAJON",
        "zip": "92021",
        "email": "GHANDY_BLBOL@YAHOO.COM",
        "dateOfBirth": "1979-04-18T12:00:00",
        "ssn": "761813936",
        "userOrders": null,
        "isSold": false,
        "id": 47865
    },
    {
        "firstName": "MARGARITA",
        "lastName": "VANDERLOOP",
        "phone": "7605860225",
        "address": "1370 CALLE JULES APT 116",
        "city": "VST",
        "state": "CA",
        "zip": "92084",
        "email": "MAGGIE@MOUNTAINVIEWLUXURYAPARTMENTS.COM",
        "dateOfBirth": "1979-09-08T12:00:00",
        "ssn": "617108142",
        "userOrders": null,
        "isSold": false,
        "id": 47939
    },
    {
        "firstName": "MARK",
        "lastName": "J",
        "phone": "8284354757",
        "address": "53 SWEETPEA LN",
        "city": "ZRCNA",
        "state": "NC",
        "zip": "28790",
        "email": "BILLYGOAT.BOUNDS@ATT.NET",
        "dateOfBirth": "1979-10-02T12:00:00",
        "ssn": "245556573",
        "userOrders": null,
        "isSold": false,
        "id": 47958
    },
    {
        "firstName": "LAURA",
        "lastName": "KILLEBREW.",
        "phone": "8658010894",
        "address": "2911 CONNER DR",
        "city": "KODAK",
        "state": "TN",
        "zip": "37764",
        "email": "LAURABETHKILLBREW@GMAIL.COM",
        "dateOfBirth": "1979-01-31T12:00:00",
        "ssn": "404237594",
        "userOrders": null,
        "isSold": false,
        "id": 48004
    }
]