[
    {
        "firstName": "ADRIANA",
        "lastName": "GARCIA",
        "phone": "2195012705",
        "address": "3343 CRAIG DR APT 144-H",
        "city": "HAMMOND",
        "state": "IN",
        "zip": "46323",
        "email": "ACG121212@GMAIL.COM",
        "dateOfBirth": "1979-05-08T12:00:00",
        "ssn": "304028005",
        "userOrders": null,
        "isSold": false,
        "id": 101565
    },
    {
        "firstName": "DONNA",
        "lastName": "WINDHAM",
        "phone": "1111110001",
        "address": "APT 262",
        "city": "SPRING",
        "state": "BROOKHAVEN",
        "zip": "77386",
        "email": "DONNAWINDHAM@YAHOO.COM",
        "dateOfBirth": "1979-01-15T12:00:00",
        "ssn": "456479566",
        "userOrders": null,
        "isSold": false,
        "id": 101592
    },
    {
        "firstName": "TIFFANY",
        "lastName": "GOODMAN",
        "phone": "1111110002",
        "address": "230 LAKEVIEW CIR",
        "city": "BROWNSVILLE",
        "state": "TN",
        "zip": "38012",
        "email": "TIFFANYGOODMAN104@YAHOO.COM",
        "dateOfBirth": "1979-11-16T12:00:00",
        "ssn": "438414349",
        "userOrders": null,
        "isSold": false,
        "id": 101696
    },
    {
        "firstName": "MOHAMMED",
        "lastName": "YAHYA",
        "phone": "2489829712",
        "address": "6716 DE MOSS DR APT 49",
        "city": "NOVI",
        "state": "TX",
        "zip": "48377",
        "email": "THAREQYAHYA@YAHOO.COM",
        "dateOfBirth": "1979-06-19T12:00:00",
        "ssn": "369212407",
        "userOrders": null,
        "isSold": false,
        "id": 101800
    },
    {
        "firstName": "DOLORES",
        "lastName": "ENRIQUEZ",
        "phone": "2093009387",
        "address": "2327 SWAINSONS HAWK ST",
        "city": "STKN",
        "state": "CA",
        "zip": "95209",
        "email": "MAY.JOHN2008@GMAIL.COM",
        "dateOfBirth": "1979-04-27T12:00:00",
        "ssn": "606071105",
        "userOrders": null,
        "isSold": false,
        "id": 101885
    },
    {
        "firstName": "JASON",
        "lastName": "CATCHOT",
        "phone": "2514026066",
        "address": "108 LE HARDY DR",
        "city": "SAVH",
        "state": "GA",
        "zip": "31405",
        "email": "JMCATCHOT@GMAIL.COM",
        "dateOfBirth": "1979-02-26T12:00:00",
        "ssn": "427576694",
        "userOrders": null,
        "isSold": false,
        "id": 101945
    },
    {
        "firstName": "JACOB",
        "lastName": "OLSON",
        "phone": "7042360077",
        "address": "8915 MAGNOLIA ESTATES DR",
        "city": "CORNELIUS",
        "state": "NC",
        "zip": "28031",
        "email": "JACOBJOLSON11@GMAIL.COM",
        "dateOfBirth": "1979-08-12T12:00:00",
        "ssn": "473153014",
        "userOrders": null,
        "isSold": false,
        "id": 102001
    },
    {
        "firstName": "SHAUN",
        "lastName": "P",
        "phone": "3185733598",
        "address": "2030 FORD ST",
        "city": "SHREVEPORT",
        "state": "LA",
        "zip": "71101",
        "email": "SHAUN.DUPLESSIS79@GMAIL.COM",
        "dateOfBirth": "1979-01-08T12:00:00",
        "ssn": "439355268",
        "userOrders": null,
        "isSold": false,
        "id": 102002
    },
    {
        "firstName": "XAVIER",
        "lastName": "ZULUETA",
        "phone": "8065001127",
        "address": "223 INDIANA AVE APT 1204",
        "city": "LUBBOCK",
        "state": "TX",
        "zip": "79415",
        "email": "X_ZULU@YAHOO.COM",
        "dateOfBirth": "1979-05-20T12:00:00",
        "ssn": "395835996",
        "userOrders": null,
        "isSold": false,
        "id": 102006
    },
    {
        "firstName": "MAURO",
        "lastName": "PARINI",
        "phone": "9368272555",
        "address": "2609 LINK RD",
        "city": "HOUSTON",
        "state": "TX",
        "zip": "77009",
        "email": "MAURO.PARINI@LAMBERTI.COM",
        "dateOfBirth": "1979-11-23T12:00:00",
        "ssn": "598254272",
        "userOrders": null,
        "isSold": false,
        "id": 102233
    },
    {
        "firstName": "ALEX",
        "lastName": "KINDLE",
        "phone": "7732437356",
        "address": "6535 S WOODLAWN AVE UNIT 3N",
        "city": "CHGO",
        "state": "IL",
        "zip": "60637",
        "email": "BIGGAL75@YAHOO.COM",
        "dateOfBirth": "1979-10-13T12:00:00",
        "ssn": "329707504",
        "userOrders": null,
        "isSold": false,
        "id": 102249
    },
    {
        "firstName": "CHAD",
        "lastName": "KIRKWOOD",
        "phone": "8644254544",
        "address": "129 HENDERSON PLACE DR",
        "city": "BENTON TWP",
        "state": "SC",
        "zip": "49022",
        "email": "GO-BLUE-16@HOTMAIL.COM",
        "dateOfBirth": "1979-03-03T12:00:00",
        "ssn": "383908232",
        "userOrders": null,
        "isSold": false,
        "id": 102267
    },
    {
        "firstName": "HAESUN",
        "lastName": "JON",
        "phone": "9257852781",
        "address": "729 LEAVENWORTH ST APT 41",
        "city": "SF",
        "state": "FRANCISCO",
        "zip": "94109",
        "email": "HAESUNJON@GMAIL.COM",
        "dateOfBirth": "1979-02-24T12:00:00",
        "ssn": "621414388",
        "userOrders": null,
        "isSold": true,
        "id": 102275
    },
    {
        "firstName": "GERARDO",
        "lastName": "SALAS",
        "phone": "8303136095",
        "address": "1817 JUAREZ AVE APT B",
        "city": "LAREDO",
        "state": "TX",
        "zip": "78040",
        "email": "GSALAS264@GMAIL.COM",
        "dateOfBirth": "1979-04-21T12:00:00",
        "ssn": "460957465",
        "userOrders": null,
        "isSold": false,
        "id": 102455
    },
    {
        "firstName": "PEDRO",
        "lastName": "GONZALEZ",
        "phone": "6182034592",
        "address": "1316 EILEEN ST",
        "city": "COLNSVL",
        "state": "IL",
        "zip": "62234",
        "email": "DELIAVACA42@GMAIL.COM",
        "dateOfBirth": "1979-12-02T12:00:00",
        "ssn": "631092547",
        "userOrders": null,
        "isSold": false,
        "id": 102603
    }
]