[
    {
        "firstName": "NICHOLAS",
        "lastName": "TURNER",
        "phone": "9062396403",
        "address": "279 NARVAEZ DR",
        "city": "MIMS",
        "state": "FL",
        "zip": "32754",
        "email": "NICHOLASHTURNER@YAHOO.COM",
        "dateOfBirth": "1980-04-25T12:00:00",
        "ssn": "362925393",
        "userOrders": null,
        "isSold": false,
        "id": 96802
    },
    {
        "firstName": "DILLON",
        "lastName": "EVANS",
        "phone": "6308092360",
        "address": "19 MARNEL RD",
        "city": "MONTGRY",
        "state": "IL",
        "zip": "60538",
        "email": "PASTORDILLONEVANS@GMAIL.COM",
        "dateOfBirth": "1980-07-02T12:00:00",
        "ssn": "353682733",
        "userOrders": null,
        "isSold": false,
        "id": 96832
    },
    {
        "firstName": "FELIPE",
        "lastName": "ZAVALZA",
        "phone": "9518364387",
        "address": "1073 OAK GLEN LN",
        "city": "CLTN",
        "state": "CA",
        "zip": "92324",
        "email": "FIZDOG@ATT.NET",
        "dateOfBirth": "1980-08-19T12:00:00",
        "ssn": "552637715",
        "userOrders": null,
        "isSold": false,
        "id": 96855
    },
    {
        "firstName": "DANIELLE",
        "lastName": "STIDHAM",
        "phone": "5133839982",
        "address": "2042 WAGON WHEEL DR",
        "city": "TRENTON",
        "state": "OH",
        "zip": "45067",
        "email": "BSTID24@AOL.COM",
        "dateOfBirth": "1980-11-09T12:00:00",
        "ssn": "302782078",
        "userOrders": null,
        "isSold": false,
        "id": 96858
    },
    {
        "firstName": "SHARON",
        "lastName": "PUTNAM",
        "phone": "7706645772",
        "address": "100 FORREST VIEW TER",
        "city": "JOHNS CREEK",
        "state": "CREEK",
        "zip": "30022",
        "email": "SEPUTNAM@BELLSOUTH.NET",
        "dateOfBirth": "1980-01-01T12:00:00",
        "ssn": "254114393",
        "userOrders": null,
        "isSold": false,
        "id": 96984
    },
    {
        "firstName": "JACKIE",
        "lastName": "KENNEDY",
        "phone": "6014975050",
        "address": "902 PINE GROVE RD",
        "city": "MAGEE",
        "state": "MS",
        "zip": "39111",
        "email": "NOREPLY@ATT.NET",
        "dateOfBirth": "1980-01-01T12:00:00",
        "ssn": "427061387",
        "userOrders": null,
        "isSold": false,
        "id": 97008
    },
    {
        "firstName": "JUSTIN",
        "lastName": "DAUER",
        "phone": "6143971339",
        "address": "7159 BILLY GOAT DR",
        "city": "COLUMBUS",
        "state": "ALBANY",
        "zip": "43054",
        "email": "DAUER1499@GMAIL.COM",
        "dateOfBirth": "1980-09-25T12:00:00",
        "ssn": "271924869",
        "userOrders": null,
        "isSold": false,
        "id": 97094
    },
    {
        "firstName": "KEAWNA.",
        "lastName": "DOUGLAS",
        "phone": "9893976011",
        "address": "275 SUNFLOWER LN",
        "city": "SAGINAW",
        "state": "GA",
        "zip": "48601",
        "email": "MSKEDY@YAHOO.COM",
        "dateOfBirth": "1980-07-06T12:00:00",
        "ssn": "362886846",
        "userOrders": null,
        "isSold": false,
        "id": 97158
    },
    {
        "firstName": "TIMOTHY",
        "lastName": "SWANSON",
        "phone": "4147190185",
        "address": "APT 5",
        "city": "WAUKESHA",
        "state": "KENSINGTON",
        "zip": "53188",
        "email": "TJSWANSON@UWALUMNI.COM",
        "dateOfBirth": "1980-04-11T12:00:00",
        "ssn": "394904533",
        "userOrders": null,
        "isSold": false,
        "id": 97192
    },
    {
        "firstName": "COLIN",
        "lastName": "SANTILLAN",
        "phone": "8325281331",
        "address": "1307 W GRAY ST",
        "city": "HOUSTON",
        "state": "TX",
        "zip": "77019",
        "email": "CSANTILLAN@GMAIL.COM",
        "dateOfBirth": "1980-05-15T12:00:00",
        "ssn": "633400603",
        "userOrders": null,
        "isSold": false,
        "id": 97375
    },
    {
        "firstName": "JULIO",
        "lastName": "CRUZ",
        "phone": "5594808373",
        "address": "356 6TH ST",
        "city": "ORG CV",
        "state": "COVE",
        "zip": "93646",
        "email": "GONZALESALEX1997@GMAIL.COM",
        "dateOfBirth": "1980-07-10T12:00:00",
        "ssn": "604317925",
        "userOrders": null,
        "isSold": true,
        "id": 97436
    },
    {
        "firstName": "LESLIE",
        "lastName": "JUDA",
        "phone": "7138708772",
        "address": "1302 BROADWAY ST APT 119",
        "city": "PEARLAND",
        "state": "TX",
        "zip": "77581",
        "email": "LJUDA@ATT.NET",
        "dateOfBirth": "1980-12-09T12:00:00",
        "ssn": "460670370",
        "userOrders": null,
        "isSold": false,
        "id": 97532
    },
    {
        "firstName": "GEORGIA",
        "lastName": "WILLIAMSON",
        "phone": "7346731140",
        "address": "5376 CORNELL ST",
        "city": "DEARBORN HEIGHTS",
        "state": "HTS",
        "zip": "48125",
        "email": "GWILLIA7@GMAIL.COM",
        "dateOfBirth": "1980-10-05T12:00:00",
        "ssn": "278763907",
        "userOrders": null,
        "isSold": false,
        "id": 97622
    },
    {
        "firstName": "TAVARES",
        "lastName": "ROBINSON",
        "phone": "9725721125",
        "address": "9312 TIMBERBLUFF RD",
        "city": "DALLAS",
        "state": "TX",
        "zip": "75249",
        "email": "TAVARESROBINSON@ATT.NET",
        "dateOfBirth": "1980-04-01T12:00:00",
        "ssn": "426373344",
        "userOrders": null,
        "isSold": false,
        "id": 97639
    },
    {
        "firstName": "CHRISTY",
        "lastName": "RUZGA",
        "phone": "3172946705",
        "address": "1037 CREEKWOOD LN",
        "city": "FRANKLIN",
        "state": "IN",
        "zip": "46131",
        "email": "CHRISTYRUZGA@HOTMAIL.COM",
        "dateOfBirth": "1980-04-29T12:00:00",
        "ssn": "310864447",
        "userOrders": null,
        "isSold": false,
        "id": 97650
    }
]