[
    {
        "firstName": "MARK",
        "lastName": "TOCZEK",
        "phone": "7733927274",
        "address": "7054 W 73RD PL",
        "city": "BRDGVW",
        "state": "IL",
        "zip": "60638",
        "email": "MTOCZE1@HOTMAIL.COM",
        "dateOfBirth": "1981-07-31T12:00:00",
        "ssn": "346706778",
        "userOrders": null,
        "isSold": false,
        "id": 40649
    },
    {
        "firstName": "MAX",
        "lastName": "ISAACS",
        "phone": "9195339857",
        "address": "315 PINE CREEK DR",
        "city": "RAL",
        "state": "NC",
        "zip": "27604",
        "email": "NCSOLARMAX@GMAIL.COM",
        "dateOfBirth": "1981-07-10T12:00:00",
        "ssn": "244558024",
        "userOrders": null,
        "isSold": false,
        "id": 40659
    },
    {
        "firstName": "DANIEL",
        "lastName": "CISNEROS",
        "phone": "7142290926",
        "address": "200 S DELANO ST APT 3",
        "city": "ANH",
        "state": "CA",
        "zip": "92804",
        "email": "DNL_CISNEROS@ATT.NET",
        "dateOfBirth": "1981-02-18T12:00:00",
        "ssn": "562672208",
        "userOrders": null,
        "isSold": false,
        "id": 40721
    },
    {
        "firstName": "JASON",
        "lastName": "GLOVER",
        "phone": "9196195384",
        "address": "8904 CARNOUSTIE WAY",
        "city": "RAL",
        "state": "NC",
        "zip": "27613",
        "email": "JGLOVER1015@GMAIL.COM",
        "dateOfBirth": "1981-04-08T12:00:00",
        "ssn": "244512638",
        "userOrders": null,
        "isSold": false,
        "id": 40730
    },
    {
        "firstName": "ANDREW",
        "lastName": "MANGO",
        "phone": "9512185447",
        "address": "914 WYVAL AVE",
        "city": "COR",
        "state": "CA",
        "zip": "92882",
        "email": "MANGOS.MADNESS@YAHOO.COM",
        "dateOfBirth": "1981-02-11T12:00:00",
        "ssn": "611015770",
        "userOrders": null,
        "isSold": false,
        "id": 40829
    },
    {
        "firstName": "BRYAN",
        "lastName": "LAPID",
        "phone": "2489782417",
        "address": "2895 SIMPSON DR",
        "city": "ROCHESTER HILLS",
        "state": "HLS",
        "zip": "48309",
        "email": "NAELAPID@YAHOO.COM",
        "dateOfBirth": "1981-05-03T12:00:00",
        "ssn": "363927442",
        "userOrders": null,
        "isSold": true,
        "id": 41014
    },
    {
        "firstName": "VICTORIA",
        "lastName": "SIMPSON",
        "phone": "8035287684",
        "address": "247 BROOKSDALE DR",
        "city": "COLA",
        "state": "SC",
        "zip": "29229",
        "email": "VSIMPSON616@HOTMAIL.COM",
        "dateOfBirth": "1981-06-16T12:00:00",
        "ssn": "487868684",
        "userOrders": null,
        "isSold": false,
        "id": 41045
    },
    {
        "firstName": "SEQUITA",
        "lastName": "TYUS",
        "phone": "7733540730",
        "address": "1413 S SAWYER AVE FL 3",
        "city": "CHGO",
        "state": "IL",
        "zip": "60623",
        "email": "SEQUITA_TYUS@YAHOO.COM",
        "dateOfBirth": "1981-06-22T12:00:00",
        "ssn": "357704652",
        "userOrders": null,
        "isSold": false,
        "id": 41057
    },
    {
        "firstName": "RYAN",
        "lastName": "SIFFRING",
        "phone": "3144094407",
        "address": "317 MAGNOLIA VALLEY DR",
        "city": "ST CHARLES",
        "state": "FALLON",
        "zip": "63301",
        "email": "SIFFRING@GMAIL.COM",
        "dateOfBirth": "1981-03-04T12:00:00",
        "ssn": "507069511",
        "userOrders": null,
        "isSold": false,
        "id": 41157
    },
    {
        "firstName": "ALLISON",
        "lastName": "MEWBORN",
        "phone": "7073912239",
        "address": "1636 MARTIN ST",
        "city": "LKPRT",
        "state": "CA",
        "zip": "95453",
        "email": "ALLISON.MEWBORN@GMAIL.COM",
        "dateOfBirth": "1981-10-08T12:00:00",
        "ssn": "573692763",
        "userOrders": null,
        "isSold": false,
        "id": 41211
    },
    {
        "firstName": "BINU",
        "lastName": "THOMAS",
        "phone": "9492044607",
        "address": "APT B",
        "city": "MARYLAND HEIGHTS",
        "state": "GLENMEADE",
        "zip": "63043",
        "email": "BINZTHOMAS@GMAIL.COM",
        "dateOfBirth": "1981-08-22T12:00:00",
        "ssn": "702299047",
        "userOrders": null,
        "isSold": false,
        "id": 41227
    },
    {
        "firstName": "RUI",
        "lastName": "YAN",
        "phone": "6267597956",
        "address": "DBA BLESSING MORALITY MASSAGE",
        "city": "GG",
        "state": "FOXGLOVE",
        "zip": "92844",
        "email": "JIAJIA060322@126.COM",
        "dateOfBirth": "1981-04-06T12:00:00",
        "ssn": "612813754",
        "userOrders": null,
        "isSold": false,
        "id": 41297
    },
    {
        "firstName": "JAMES",
        "lastName": "ROQUEMORE",
        "phone": "4048843278",
        "address": "69 ANNANDALE DR",
        "city": "DLS",
        "state": "GA",
        "zip": "30132",
        "email": "LROQUEMORE@GMAIL.COM",
        "dateOfBirth": "1981-07-27T12:00:00",
        "ssn": "256632438",
        "userOrders": null,
        "isSold": false,
        "id": 41447
    },
    {
        "firstName": "SCOTT",
        "lastName": "PELL",
        "phone": "6166696847",
        "address": "3686 WESTBEECH CT",
        "city": "GEORGETOWN TWP",
        "state": "MI",
        "zip": "49426",
        "email": "SCOTT.J.PELL@MARSH.COM",
        "dateOfBirth": "1981-01-01T12:00:00",
        "ssn": "377981064",
        "userOrders": null,
        "isSold": false,
        "id": 41455
    },
    {
        "firstName": "JOSHUA",
        "lastName": "ELLIOTT",
        "phone": "4077177378",
        "address": "7609 BIPE LN",
        "city": "ORL",
        "state": "FL",
        "zip": "32822",
        "email": "JB.ELLIOTT@YAHOO.COM",
        "dateOfBirth": "1981-05-14T12:00:00",
        "ssn": "601604156",
        "userOrders": null,
        "isSold": false,
        "id": 41490
    }
]