[
    {
        "firstName": "TIFFANY",
        "lastName": "HART",
        "phone": "6204911971",
        "address": "616 CHARITON ST",
        "city": "KINGMAN",
        "state": "KS",
        "zip": "67068",
        "email": "TFFNY_HRT@YMAIL.COM",
        "dateOfBirth": "1987-05-21T12:00:00",
        "ssn": "513929315",
        "userOrders": null,
        "isSold": false,
        "id": 78797
    },
    {
        "firstName": "DANIELLE",
        "lastName": "DAVIS",
        "phone": "9124847895",
        "address": "110 HUCKLEBERRY CT",
        "city": "ATL",
        "state": "GA",
        "zip": "30339",
        "email": "DJOSEYDAVIS@YAHOO.COM",
        "dateOfBirth": "1987-05-09T12:00:00",
        "ssn": "259730511",
        "userOrders": null,
        "isSold": false,
        "id": 78811
    },
    {
        "firstName": "BRANDY",
        "lastName": "ELLIS",
        "phone": "8327442406",
        "address": "4522 SYLVANFIELD DR APT 904",
        "city": "HOUSTON",
        "state": "TX",
        "zip": "77014",
        "email": "ELLISCD32@GMAIL.COM",
        "dateOfBirth": "1987-01-06T12:00:00",
        "ssn": "636185531",
        "userOrders": null,
        "isSold": false,
        "id": 78881
    },
    {
        "firstName": "ASADULLAH",
        "lastName": "AMANYAR",
        "phone": "5103056909",
        "address": "5085 LOCH LN",
        "city": "SN LDRO",
        "state": "LEANDRO",
        "zip": "94578",
        "email": "ASADULLAH.AMANYAR@GMAIL.COM",
        "dateOfBirth": "1987-04-15T12:00:00",
        "ssn": "899286318",
        "userOrders": null,
        "isSold": false,
        "id": 79060
    },
    {
        "firstName": "JULIAN",
        "lastName": "HAYES",
        "phone": "8175763864",
        "address": "APT 2104",
        "city": "HALTOM CITY",
        "state": "FOSSIL",
        "zip": "76137",
        "email": "JULIANWHAYES@YAHOO.COM",
        "dateOfBirth": "1987-02-19T12:00:00",
        "ssn": "632204093",
        "userOrders": null,
        "isSold": false,
        "id": 79160
    },
    {
        "firstName": "BRITTANY",
        "lastName": "JACKSON",
        "phone": "5415151424",
        "address": "3976 SHASTA ST APT 101",
        "city": "PAC BCH",
        "state": "DIEGO",
        "zip": "92109",
        "email": "BRITTSY1414@GMAIL.COM",
        "dateOfBirth": "1987-10-29T12:00:00",
        "ssn": "544296087",
        "userOrders": null,
        "isSold": false,
        "id": 79176
    },
    {
        "firstName": "MOLLY",
        "lastName": "ESTES",
        "phone": "7609531265",
        "address": "12668 JADE RD",
        "city": "SUNYVL",
        "state": "CA",
        "zip": "94086",
        "email": "MOLLYKESTES@GMAIL.COM",
        "dateOfBirth": "1987-05-02T12:00:00",
        "ssn": "607165219",
        "userOrders": null,
        "isSold": false,
        "id": 79198
    },
    {
        "firstName": "KELLY'S",
        "lastName": "KANS",
        "phone": "7705273126",
        "address": "38 SPRING DR",
        "city": "HRM",
        "state": "GA",
        "zip": "30141",
        "email": "KELLYKANS@ATT.NET",
        "dateOfBirth": "1987-10-10T12:00:00",
        "ssn": "574227424",
        "userOrders": null,
        "isSold": false,
        "id": 79302
    },
    {
        "firstName": "SHATISH",
        "lastName": "SAMPAT",
        "phone": "4075875790",
        "address": "7917 SHOALS DR APT F",
        "city": "OCOEE",
        "state": "FL",
        "zip": "34761",
        "email": "SSAMPAT.SS11@GMAIL.COM",
        "dateOfBirth": "1987-05-27T12:00:00",
        "ssn": "731105844",
        "userOrders": null,
        "isSold": false,
        "id": 79350
    },
    {
        "firstName": "CHRISTOPHER",
        "lastName": "LAUDICINA",
        "phone": "5614017223",
        "address": "PO BOX 1064",
        "city": "JUP",
        "state": "FL",
        "zip": "33458",
        "email": "NOEMAILATT@CLEARLINK.COM",
        "dateOfBirth": "1987-09-13T12:00:00",
        "ssn": "589782102",
        "userOrders": null,
        "isSold": false,
        "id": 79352
    },
    {
        "firstName": "REBECCA",
        "lastName": "HAWKINSON-GONZALEZ",
        "phone": "9253541859",
        "address": "1305 SAINT CLAIRE DR",
        "city": "LAF",
        "state": "CA",
        "zip": "94549",
        "email": "REBECCAHAWKINSON@LIVE.COM",
        "dateOfBirth": "1987-01-21T12:00:00",
        "ssn": "615366713",
        "userOrders": null,
        "isSold": false,
        "id": 79353
    },
    {
        "firstName": "TAYLOR",
        "lastName": "CONRADI",
        "phone": "8502074307",
        "address": "215 APRIL DR",
        "city": "ANTIOCH",
        "state": "HICKORY",
        "zip": "37013",
        "email": "TCCONRADI@GMAIL.COM",
        "dateOfBirth": "1987-07-01T12:00:00",
        "ssn": "424317727",
        "userOrders": null,
        "isSold": false,
        "id": 79399
    },
    {
        "firstName": "EMANUEL",
        "lastName": "SHOCKLEY",
        "phone": "3863089433",
        "address": "263 ALMANSA RD",
        "city": "ST AUG",
        "state": "AUGUSTINE",
        "zip": "32086",
        "email": "EGSHOCKLEY@AOL.COM",
        "dateOfBirth": "1987-01-05T12:00:00",
        "ssn": "611030773",
        "userOrders": null,
        "isSold": false,
        "id": 79431
    },
    {
        "firstName": "DONNA",
        "lastName": "LEHR",
        "phone": "3302842831",
        "address": "1484 GALWAY BND S",
        "city": "PLAIN TWP",
        "state": "OH",
        "zip": "44708",
        "email": "DLEHR0515@STARKSTATE.NET",
        "dateOfBirth": "1987-05-15T12:00:00",
        "ssn": "283861988",
        "userOrders": null,
        "isSold": true,
        "id": 79436
    },
    {
        "firstName": "CADAN",
        "lastName": "CHASEZ",
        "phone": "1111110001",
        "address": "8050 PIERRE DR",
        "city": "JKVL",
        "state": "FL",
        "zip": "32210",
        "email": "ELITE.DIRECTOR09@GMAIL.COM",
        "dateOfBirth": "1987-08-13T12:00:00",
        "ssn": "645289918",
        "userOrders": null,
        "isSold": false,
        "id": 79492
    }
]