[
    {
        "firstName": "TAYLOR",
        "lastName": "HARRIS",
        "phone": "8323143075",
        "address": "4947 BRAESHEATHER DR",
        "city": "HOUSTON",
        "state": "TX",
        "zip": "77096",
        "email": "HARRISTAYLOR6994@YAHOO.COM",
        "dateOfBirth": "1994-06-09T12:00:00",
        "ssn": "635427642",
        "userOrders": null,
        "isSold": true,
        "id": 18319
    },
    {
        "firstName": "HARRISON",
        "lastName": "JONES",
        "phone": "4178727125",
        "address": "1447 E MCGEE ST",
        "city": "SPRINGFIELD",
        "state": "MO",
        "zip": "65804",
        "email": "HARRISONJONES0341@YAHOO.COM",
        "dateOfBirth": "1994-08-04T12:00:00",
        "ssn": "486110924",
        "userOrders": null,
        "isSold": false,
        "id": 18462
    },
    {
        "firstName": "ERIC",
        "lastName": "CASTANON",
        "phone": "7604705463",
        "address": "242 JONES CT",
        "city": "VST",
        "state": "CA",
        "zip": "92083",
        "email": "CHICOCAST94@GMAIL.COM",
        "dateOfBirth": "1994-01-16T12:00:00",
        "ssn": "411758518",
        "userOrders": null,
        "isSold": true,
        "id": 18759
    },
    {
        "firstName": "TYLER",
        "lastName": "GRAY",
        "phone": "8174086746",
        "address": "APT 106",
        "city": "HURST",
        "state": "SOTOGRANDE",
        "zip": "76053",
        "email": "HOLOOSHA@YAHOO.COM",
        "dateOfBirth": "1994-01-02T12:00:00",
        "ssn": "627464823",
        "userOrders": null,
        "isSold": false,
        "id": 18766
    },
    {
        "firstName": "WENDY",
        "lastName": "PARRA",
        "phone": "6615465678",
        "address": "PO BOX 11746",
        "city": "ERLMT",
        "state": "CA",
        "zip": "93219",
        "email": "02CESAR26@GMAIL.COM",
        "dateOfBirth": "1994-11-07T12:00:00",
        "ssn": "614356153",
        "userOrders": null,
        "isSold": true,
        "id": 19046
    },
    {
        "firstName": "ADISON",
        "lastName": "PICCH",
        "phone": "4048622683",
        "address": "5011 VICKERY BLVD",
        "city": "DALLAS",
        "state": "TX",
        "zip": "75204",
        "email": "ADISON.PICCHI@GMAIL.COM",
        "dateOfBirth": "1994-05-12T12:00:00",
        "ssn": "309150060",
        "userOrders": null,
        "isSold": true,
        "id": 19161
    },
    {
        "firstName": "ANTHONY",
        "lastName": "KALEIWAHEA",
        "phone": "8122390887",
        "address": "1726 SE WESTMORELAND BLVD",
        "city": "P*S*L",
        "state": "ST",
        "zip": "34983",
        "email": "AKKALEIWAHEA@OUTLOOK.COM",
        "dateOfBirth": "1994-08-30T12:00:00",
        "ssn": "576690122",
        "userOrders": null,
        "isSold": true,
        "id": 19164
    },
    {
        "firstName": "DOMINIQ",
        "lastName": "WRIGHT",
        "phone": "4796859106",
        "address": "517 HIMEBAUGH CT",
        "city": "INDIANAPOLIS",
        "state": "IN",
        "zip": "46231",
        "email": "WRIGHTFAMILYDK@GMAIL.COM",
        "dateOfBirth": "1994-05-30T12:00:00",
        "ssn": "295691377",
        "userOrders": null,
        "isSold": true,
        "id": 19234
    },
    {
        "firstName": "GLORIA",
        "lastName": "WOO",
        "phone": "6262219862",
        "address": "900 N BROADWAY APT 329",
        "city": "LA",
        "state": "ANGELES",
        "zip": "90012",
        "email": "BRYCECIRE@GMAIL.COM",
        "dateOfBirth": "1994-08-05T12:00:00",
        "ssn": "774020293",
        "userOrders": null,
        "isSold": false,
        "id": 19378
    },
    {
        "firstName": "AMANDA",
        "lastName": "N",
        "phone": "7347758418",
        "address": "17400 FORT ST APT 38",
        "city": "WYANDOTTE",
        "state": "MI",
        "zip": "48192",
        "email": "AKULAKOWSKY@YAHOO.COM",
        "dateOfBirth": "1994-06-04T12:00:00",
        "ssn": "378175725",
        "userOrders": null,
        "isSold": false,
        "id": 19524
    },
    {
        "firstName": "DAMARCUS",
        "lastName": "WEISINGER",
        "phone": "8326008143",
        "address": "7110 LILAC MANOR LN",
        "city": "RICHMOND",
        "state": "TX",
        "zip": "77469",
        "email": "DMARC1994@YAHOO.COM",
        "dateOfBirth": "1994-10-21T12:00:00",
        "ssn": "635442797",
        "userOrders": null,
        "isSold": true,
        "id": 19542
    },
    {
        "firstName": "BRANDON",
        "lastName": "COBB",
        "phone": "9044389870",
        "address": "10525 MONACO DR APT 212",
        "city": "JKVL",
        "state": "FL",
        "zip": "32218",
        "email": "POPPY3489@GMAIL.COM",
        "dateOfBirth": "1994-06-22T12:00:00",
        "ssn": "591434122",
        "userOrders": null,
        "isSold": false,
        "id": 19550
    },
    {
        "firstName": "ANGELA",
        "lastName": "LISAK",
        "phone": "5863440003",
        "address": "42142 TODDMARK LN",
        "city": "CLINTON TWP",
        "state": "TWP",
        "zip": "48038",
        "email": "MATEUSZ.KOZIOL@YAHOO.COM",
        "dateOfBirth": "1994-03-26T12:00:00",
        "ssn": "369171549",
        "userOrders": null,
        "isSold": false,
        "id": 19554
    },
    {
        "firstName": "VANQUISHA",
        "lastName": "DENSON",
        "phone": "2052073001",
        "address": "2602 SUMMERLAKE DR",
        "city": "SANDY SPRINGS",
        "state": "SPRINGS",
        "zip": "30350",
        "email": "DANQUISHADENSON@YAHOO.COM",
        "dateOfBirth": "1994-09-09T12:00:00",
        "ssn": "420434121",
        "userOrders": null,
        "isSold": false,
        "id": 19750
    },
    {
        "firstName": "GEMMA",
        "lastName": "GONZALEZ",
        "phone": "7132910609",
        "address": "7305 ALMEDA GENOA RD",
        "city": "HOUSTON",
        "state": "TX",
        "zip": "77075",
        "email": "GEMMAGONZALEZ31@GMAIL.COM",
        "dateOfBirth": "1994-11-25T12:00:00",
        "ssn": "641446880",
        "userOrders": null,
        "isSold": true,
        "id": 19854
    }
]